cell_analysis_tools/__init__.py
cell_analysis_tools/flim/__init__.py
cell_analysis_tools/flim/_lifetime_image_to_rectangular_points.py
cell_analysis_tools/flim/_phasor_to_rectangular_lifetimes_array.py
cell_analysis_tools/flim/_rectangular_to_phasor_lifetimes_array.py
cell_analysis_tools/flim/bin_image.py
cell_analysis_tools/flim/draw_universal_semicircle.py
cell_analysis_tools/flim/estimate_and_shift_irf.py
cell_analysis_tools/flim/ideal_sample_phasor.py
cell_analysis_tools/flim/lifetime_to_phasor.py
cell_analysis_tools/flim/phasor_calculator.py
cell_analysis_tools/flim/phasor_calibration.py
cell_analysis_tools/flim/phasor_to_rectangular.py
cell_analysis_tools/flim/rectangular_to_phasor.py
cell_analysis_tools/flim/regionprops_omi.py
cell_analysis_tools/flim/tests.py
cell_analysis_tools/image_processing/__init__.py
cell_analysis_tools/image_processing/bin_2d.py
cell_analysis_tools/image_processing/bin_3d.py
cell_analysis_tools/image_processing/fft_image_filter.py
cell_analysis_tools/image_processing/fill_and_label_rois.py
cell_analysis_tools/image_processing/kmeans_threshold.py
cell_analysis_tools/image_processing/mito_segmentation.py
cell_analysis_tools/image_processing/normalize.py
cell_analysis_tools/image_processing/remove_small_areas_fill_regions.py
cell_analysis_tools/image_processing/rgb2gray.py
cell_analysis_tools/image_processing/rgb2labels.py
cell_analysis_tools/image_processing/sum_pool_3d.py
cell_analysis_tools/image_processing/four_color_theorem/__init__.py
cell_analysis_tools/image_processing/four_color_theorem/four_color_theorem_original.py
cell_analysis_tools/image_processing/four_color_theorem/four_color_theorem_to_unique_values.py
cell_analysis_tools/image_processing/four_color_theorem/four_colors.py
cell_analysis_tools/io/__init__.py
cell_analysis_tools/io/load_image.py
cell_analysis_tools/io/load_sdt.py
cell_analysis_tools/io/read_asc.py
cell_analysis_tools/metrics/__init__.py
cell_analysis_tools/metrics/average_relative_performance.py
cell_analysis_tools-1.0.1.dist-info/LICENSE
cell_analysis_tools-1.0.1.dist-info/METADATA
cell_analysis_tools-1.0.1.dist-info/WHEEL
cell_analysis_tools-1.0.1.dist-info/entry_points.txt
cell_analysis_tools-1.0.1.dist-info/top_level.txt
cell_analysis_tools-1.0.1.dist-info/RECORD
