Metadata-Version: 2.1
Name: cell-analysis-tools
Version: 1.0.1
Summary: cell analysis tools
Author: Emmanuel Contreras Guzman
Author-email: Emmanuel Contreras <econtreras@wisc.edu>
License: GNU GENERAL PUBLIC LICENSE
Project-URL: Homepage, https://github.com/skalalab/cell-analysis-tools
Keywords: cell,analysis,tools
Classifier: License :: OSI Approved :: GNU General Public License v3 (GPLv3)
Classifier: Programming Language :: Python
Classifier: Programming Language :: Python :: 3
Requires-Python: >=3.9
License-File: LICENSE
Requires-Dist: read-roi
Requires-Dist: umap-learn
Requires-Dist: scikit-image
Requires-Dist: scikit-learn
Requires-Dist: matplotlib
Requires-Dist: pandas
Requires-Dist: tomli ; python_version < "3.11"
Provides-Extra: dev
Requires-Dist: black ; extra == 'dev'
Requires-Dist: bumpver ; extra == 'dev'
Requires-Dist: isort ; extra == 'dev'
Requires-Dist: pip-tools ; extra == 'dev'
Requires-Dist: pytest ; extra == 'dev'
